{
    "type": "sliders:348",
    "generator": {
        "type": "minecraft:noise",
        "seed": 11141359461848047543,
        "settings": "minecraft:amplified",
        "biome_source": {
            "seed": 11141359461848047543,
            "type": "minecraft:multi_noise",
            "biomes": [
                {
                    "biome": "minecraft:snowy_beach",
                    "parameters": {
                        "altitude": 0.08,
                        "weirdness": 1.88,
                        "offset": 0.02,
                        "temperature": -0.15,
                        "humidity": 1.22
                    }
                },
                {
                    "biome": "minecraft:wooded_badlands_plateau",
                    "parameters": {
                        "altitude": 0.29,
                        "weirdness": 0.97,
                        "offset": 0.81,
                        "temperature": 1.94,
                        "humidity": 0.53
                    }
                },
                {
                    "biome": "minecraft:mushroom_fields",
                    "parameters": {
                        "altitude": -0.97,
                        "weirdness": 0.24,
                        "offset": 0.46,
                        "temperature": -1.61,
                        "humidity": -1.08
                    }
                },
                {
                    "biome": "minecraft:ice_spikes",
                    "parameters": {
                        "altitude": 1.97,
                        "weirdness": -0.15,
                        "offset": 0.4,
                        "temperature": 1.97,
                        "humidity": 0.8
                    }
                },
                {
                    "biome": "minecraft:end_midlands",
                    "parameters": {
                        "altitude": 1.34,
                        "weirdness": 0.58,
                        "offset": 0.32,
                        "temperature": -1.59,
                        "humidity": 0.44
                    }
                },
                {
                    "biome": "minecraft:tall_birch_hills",
                    "parameters": {
                        "altitude": -0.07,
                        "weirdness": -1.8,
                        "offset": 0.36,
                        "temperature": -1.17,
                        "humidity": -1.57
                    }
                },
                {
                    "biome": "minecraft:deep_frozen_ocean",
                    "parameters": {
                        "altitude": -0.18,
                        "weirdness": -0.07,
                        "offset": 0.63,
                        "temperature": 0.13,
                        "humidity": -0.26
                    }
                },
                {
                    "biome": "minecraft:flower_forest",
                    "parameters": {
                        "altitude": -0.93,
                        "weirdness": -1.08,
                        "offset": 0.9,
                        "temperature": -1.63,
                        "humidity": -1.12
                    }
                },
                {
                    "biome": "minecraft:bamboo_jungle",
                    "parameters": {
                        "altitude": 0.39,
                        "weirdness": 2.0,
                        "offset": 0.7,
                        "temperature": -0.84,
                        "humidity": 0.4
                    }
                },
                {
                    "biome": "minecraft:badlands",
                    "parameters": {
                        "altitude": -1.63,
                        "weirdness": -1.23,
                        "offset": 0.42,
                        "temperature": -1.68,
                        "humidity": -1.55
                    }
                },
                {
                    "biome": "minecraft:lukewarm_ocean",
                    "parameters": {
                        "altitude": 1.55,
                        "weirdness": 0.29,
                        "offset": 0.34,
                        "temperature": -1.8,
                        "humidity": -0.09
                    }
                },
                {
                    "biome": "minecraft:birch_forest_hills",
                    "parameters": {
                        "altitude": 1.79,
                        "weirdness": -0.32,
                        "offset": 0.94,
                        "temperature": -0.79,
                        "humidity": -0.52
                    }
                },
                {
                    "biome": "minecraft:deep_warm_ocean",
                    "parameters": {
                        "altitude": 1.41,
                        "weirdness": 1.57,
                        "offset": 0.91,
                        "temperature": -1.81,
                        "humidity": -0.22
                    }
                },
                {
                    "biome": "minecraft:frozen_ocean",
                    "parameters": {
                        "altitude": 1.18,
                        "weirdness": 0.86,
                        "offset": 0.96,
                        "temperature": -1.47,
                        "humidity": 0.86
                    }
                },
                {
                    "biome": "minecraft:taiga_hills",
                    "parameters": {
                        "altitude": 0.43,
                        "weirdness": 0.08,
                        "offset": 0.19,
                        "temperature": -1.39,
                        "humidity": -1.29
                    }
                },
                {
                    "biome": "minecraft:giant_spruce_taiga",
                    "parameters": {
                        "altitude": -1.43,
                        "weirdness": 1.21,
                        "offset": 0.11,
                        "temperature": -0.85,
                        "humidity": -1.8
                    }
                },
                {
                    "biome": "minecraft:beach",
                    "parameters": {
                        "altitude": 0.23,
                        "weirdness": 0.39,
                        "offset": 0.2,
                        "temperature": 1.08,
                        "humidity": -1.7
                    }
                },
                {
                    "biome": "minecraft:wooded_hills",
                    "parameters": {
                        "altitude": 0.97,
                        "weirdness": 0.76,
                        "offset": 0.65,
                        "temperature": 1.15,
                        "humidity": 1.72
                    }
                },
                {
                    "biome": "minecraft:modified_jungle_edge",
                    "parameters": {
                        "altitude": 0.05,
                        "weirdness": 0.57,
                        "offset": 0.9,
                        "temperature": -0.67,
                        "humidity": 1.67
                    }
                },
                {
                    "biome": "minecraft:snowy_tundra",
                    "parameters": {
                        "altitude": -1.2,
                        "weirdness": -0.79,
                        "offset": 0.56,
                        "temperature": -0.15,
                        "humidity": -1.88
                    }
                },
                {
                    "biome": "minecraft:soul_sand_valley",
                    "parameters": {
                        "altitude": -1.15,
                        "weirdness": -0.45,
                        "offset": 0.47,
                        "temperature": -0.09,
                        "humidity": 1.58
                    }
                },
                {
                    "biome": "minecraft:swamp",
                    "parameters": {
                        "altitude": -1.65,
                        "weirdness": 1.16,
                        "offset": 0.02,
                        "temperature": 1.11,
                        "humidity": -1.99
                    }
                },
                {
                    "biome": "minecraft:snowy_taiga_hills",
                    "parameters": {
                        "altitude": 1.81,
                        "weirdness": -1.47,
                        "offset": 0.36,
                        "temperature": 1.5,
                        "humidity": 0.32
                    }
                },
                {
                    "biome": "minecraft:badlands_plateau",
                    "parameters": {
                        "altitude": -0.44,
                        "weirdness": 0.34,
                        "offset": 0.63,
                        "temperature": 1.93,
                        "humidity": 0.03
                    }
                },
                {
                    "biome": "minecraft:snowy_taiga_mountains",
                    "parameters": {
                        "altitude": 0.83,
                        "weirdness": -0.88,
                        "offset": 0.81,
                        "temperature": -1.53,
                        "humidity": -0.09
                    }
                },
                {
                    "biome": "minecraft:modified_gravelly_mountains",
                    "parameters": {
                        "altitude": 0.09,
                        "weirdness": -0.75,
                        "offset": 0.81,
                        "temperature": -0.13,
                        "humidity": 0.22
                    }
                },
                {
                    "biome": "minecraft:ocean",
                    "parameters": {
                        "altitude": -1.84,
                        "weirdness": -1.7,
                        "offset": 0.25,
                        "temperature": 1.25,
                        "humidity": 0.9
                    }
                },
                {
                    "biome": "minecraft:taiga",
                    "parameters": {
                        "altitude": 0.27,
                        "weirdness": 0.5,
                        "offset": 0.23,
                        "temperature": 1.94,
                        "humidity": 1.05
                    }
                },
                {
                    "biome": "minecraft:end_highlands",
                    "parameters": {
                        "altitude": 1.67,
                        "weirdness": 0.98,
                        "offset": 0.25,
                        "temperature": 0.13,
                        "humidity": 0.72
                    }
                },
                {
                    "biome": "minecraft:warm_ocean",
                    "parameters": {
                        "altitude": 1.28,
                        "weirdness": -1.41,
                        "offset": 0.35,
                        "temperature": 0.45,
                        "humidity": 0.68
                    }
                },
                {
                    "biome": "minecraft:modified_wooded_badlands_plateau",
                    "parameters": {
                        "altitude": -1.44,
                        "weirdness": 1.56,
                        "offset": 0.99,
                        "temperature": 1.69,
                        "humidity": -1.18
                    }
                },
                {
                    "biome": "minecraft:wooded_mountains",
                    "parameters": {
                        "altitude": -0.4,
                        "weirdness": -0.45,
                        "offset": 0.83,
                        "temperature": -1.81,
                        "humidity": -0.82
                    }
                },
                {
                    "biome": "minecraft:stone_shore",
                    "parameters": {
                        "altitude": 0.53,
                        "weirdness": 1.6,
                        "offset": 0.41,
                        "temperature": -0.74,
                        "humidity": -0.56
                    }
                },
                {
                    "biome": "minecraft:end_barrens",
                    "parameters": {
                        "altitude": -1.7,
                        "weirdness": 1.54,
                        "offset": 0.49,
                        "temperature": -1.76,
                        "humidity": -0.63
                    }
                },
                {
                    "biome": "minecraft:swamp_hills",
                    "parameters": {
                        "altitude": 0.35,
                        "weirdness": -0.97,
                        "offset": 0.9,
                        "temperature": 1.33,
                        "humidity": -1.52
                    }
                },
                {
                    "biome": "minecraft:warped_forest",
                    "parameters": {
                        "altitude": -1.14,
                        "weirdness": 0.66,
                        "offset": 0.6,
                        "temperature": -1.83,
                        "humidity": -0.78
                    }
                },
                {
                    "biome": "minecraft:eroded_badlands",
                    "parameters": {
                        "altitude": -1.85,
                        "weirdness": 0.68,
                        "offset": 0.47,
                        "temperature": -1.41,
                        "humidity": 0.28
                    }
                },
                {
                    "biome": "minecraft:savanna",
                    "parameters": {
                        "altitude": -0.65,
                        "weirdness": -0.65,
                        "offset": 0.63,
                        "temperature": 1.91,
                        "humidity": -0.07
                    }
                },
                {
                    "biome": "minecraft:mountains",
                    "parameters": {
                        "altitude": 1.19,
                        "weirdness": -0.77,
                        "offset": 0.66,
                        "temperature": 1.21,
                        "humidity": -1.96
                    }
                },
                {
                    "biome": "minecraft:cold_ocean",
                    "parameters": {
                        "altitude": 1.07,
                        "weirdness": -0.85,
                        "offset": 0.56,
                        "temperature": -0.18,
                        "humidity": -0.18
                    }
                },
                {
                    "biome": "minecraft:savanna_plateau",
                    "parameters": {
                        "altitude": -1.91,
                        "weirdness": -0.01,
                        "offset": 0.87,
                        "temperature": -1.83,
                        "humidity": 1.28
                    }
                },
                {
                    "biome": "minecraft:mountain_edge",
                    "parameters": {
                        "altitude": -1.77,
                        "weirdness": 0.74,
                        "offset": 0.99,
                        "temperature": 0.27,
                        "humidity": 1.62
                    }
                },
                {
                    "biome": "minecraft:small_end_islands",
                    "parameters": {
                        "altitude": 0.98,
                        "weirdness": -0.35,
                        "offset": 0.0,
                        "temperature": -1.31,
                        "humidity": -1.05
                    }
                },
                {
                    "biome": "minecraft:deep_lukewarm_ocean",
                    "parameters": {
                        "altitude": 1.63,
                        "weirdness": -0.24,
                        "offset": 0.82,
                        "temperature": -0.05,
                        "humidity": -1.91
                    }
                },
                {
                    "biome": "minecraft:birch_forest",
                    "parameters": {
                        "altitude": -0.64,
                        "weirdness": -1.02,
                        "offset": 0.07,
                        "temperature": 0.95,
                        "humidity": 1.95
                    }
                }
            ],
            "altitude_noise": {
                "firstOctave": -9,
                "amplitudes": [
                    -0.48,
                    -0.43,
                    0.23,
                    0.91,
                    -0.4
                ]
            },
            "weirdness_noise": {
                "firstOctave": -6,
                "amplitudes": [
                    0.07,
                    0.7,
                    0.3
                ]
            },
            "temperature_noise": {
                "firstOctave": -6,
                "amplitudes": [
                    -0.87,
                    -0.38
                ]
            },
            "humidity_noise": {
                "firstOctave": -2,
                "amplitudes": [
                    0.97,
                    0.94
                ]
            }
        }
    }
}