{
    "type": "sliders:84",
    "generator": {
        "type": "minecraft:noise",
        "seed": 9439959529608164294,
        "settings": "minecraft:overworld",
        "biome_source": {
            "seed": 9439959529608164294,
            "type": "minecraft:checkerboard",
            "biomes": [
                "minecraft:wooded_mountains",
                "minecraft:gravelly_mountains",
                "minecraft:tall_birch_forest",
                "minecraft:birch_forest",
                "minecraft:mushroom_fields",
                "minecraft:ocean",
                "minecraft:soul_sand_valley",
                "minecraft:snowy_taiga_hills",
                "minecraft:sunflower_plains",
                "minecraft:frozen_river",
                "minecraft:taiga_hills",
                "minecraft:badlands_plateau",
                "minecraft:giant_tree_taiga_hills",
                "minecraft:bamboo_jungle_hills",
                "minecraft:birch_forest_hills",
                "minecraft:modified_jungle_edge",
                "minecraft:giant_tree_taiga",
                "minecraft:beach",
                "minecraft:modified_badlands_plateau",
                "minecraft:deep_warm_ocean",
                "minecraft:snowy_taiga",
                "minecraft:end_midlands",
                "minecraft:deep_ocean",
                "minecraft:small_end_islands",
                "minecraft:tall_birch_hills",
                "minecraft:giant_spruce_taiga_hills",
                "minecraft:lukewarm_ocean",
                "minecraft:bamboo_jungle",
                "minecraft:snowy_taiga_mountains",
                "minecraft:snowy_mountains",
                "minecraft:crimson_forest",
                "minecraft:basalt_deltas",
                "minecraft:mountain_edge",
                "minecraft:dark_forest_hills",
                "minecraft:dark_forest",
                "minecraft:mushroom_field_shore",
                "minecraft:desert_lakes",
                "minecraft:nether_wastes",
                "minecraft:frozen_ocean"
            ],
            "scale": 17
        }
    }
}